bilispider/__init__.py
bilispider/__main__.py
bilispider/bilispider.py
bilispider/diagnose.py
bilispider/gui.py
bilispider/headers.py
bilispider/httpserver.py
bilispider/safemode.py
bilispider/start.py
bilispider/tcppost.py
bilispider/tools.py
bilispider/version.py
bilispider/data/tid.txt
bilispider-0.9.6.dist-info/LICENSE
bilispider-0.9.6.dist-info/METADATA
bilispider-0.9.6.dist-info/WHEEL
bilispider-0.9.6.dist-info/entry_points.txt
bilispider-0.9.6.dist-info/top_level.txt
bilispider-0.9.6.dist-info/RECORD
