Metadata-Version: 2.1
Name: bilispider
Version: 0.9.6
Summary: A spider of Bilibili
Home-page: https://github.com/pangbo13/BiliSpider/
Author: pangbo
Author-email: 373108669@qq.com
License: MIT License
Platform: UNKNOWN
Classifier: Programming Language :: Python :: 3
Classifier: License :: OSI Approved :: MIT License
Classifier: Operating System :: OS Independent
Requires-Dist: requests
Requires-Dist: psutil
